orgroamtools/__init__.py
orgroamtools/_utils.py
orgroamtools/data.py
orgroamtools-0.1.5.dist-info/LICENSE
orgroamtools-0.1.5.dist-info/METADATA
orgroamtools-0.1.5.dist-info/WHEEL
orgroamtools-0.1.5.dist-info/RECORD
