Metadata-Version: 2.1
Name: orgroamtools
Version: 0.1.5
Summary: Library to aid in analysis of org-roam collections
Author: Aatmun Baxi
Author-email: abaxi@tamu.edu
Requires-Python: >=3.10,<4.0
Classifier: Programming Language :: Python :: 3
Classifier: Programming Language :: Python :: 3.10
Classifier: Programming Language :: Python :: 3.11
Classifier: Programming Language :: Python :: 3.12
Requires-Dist: networkx (>=3.2.1,<4.0.0)
Requires-Dist: orgparse (>=0.4.20231004,<0.5.0)
